{
  "project_info": {
    "project_number": "659824277303",
    "project_id": "remak-391004",
    "storage_bucket": "remak-391004.appspot.com"
  },
  "client": [
    {
      "client_info": {
        "mobilesdk_app_id": "1:659824277303:android:216f4dafbd2a0767a5ccb2",
        "android_client_info": {
          "package_name": "com.everfrost.remak"
        }
      },
      "oauth_client": [],
      "api_key": [
        {
          "current_key": "AIzaSyCMK7hskIlNh1VSbPaqdRlWCn7ts2leQAI"
        }
      ],
      "services": {
        "appinvite_service": {
          "other_platform_oauth_client": []
        }
      }
    }
  ],
  "configuration_version": "1"
}